spinqit_task_manager/__init__.py
spinqit_task_manager/qasm_submitter.py
spinqit_task_manager/test.py
spinqit_task_manager/backend/__init__.py
spinqit_task_manager/backend/backend.py
spinqit_task_manager/backend/backend_util.py
spinqit_task_manager/backend/qasm_backend.py
spinqit_task_manager/backend/spinq_cloud_backend.py
spinqit_task_manager/backend/client/__init__.py
spinqit_task_manager/backend/client/spinq_cloud_client.py
spinqit_task_manager/backend/client/spinq_session.py
spinqit_task_manager/backend/layout/__init__.py
spinqit_task_manager/backend/layout/layout.py
spinqit_task_manager/backend/layout/layout_util.py
spinqit_task_manager/backend/layout/physical_layout.py
spinqit_task_manager/backend/layout/routing_layout.py
spinqit_task_manager/backend/layout/sven_swap_mapper.py
spinqit_task_manager/compiler/__init__.py
spinqit_task_manager/compiler/compiler.py
spinqit_task_manager/compiler/ir.py
spinqit_task_manager/compiler/qasm_compiler.py
spinqit_task_manager/compiler/qasm/Qasm2ErrorListener.py
spinqit_task_manager/compiler/qasm/Qasm2EventListener.py
spinqit_task_manager/compiler/qasm/Qasm2Lexer.py
spinqit_task_manager/compiler/qasm/Qasm2Listener.py
spinqit_task_manager/compiler/qasm/Qasm2Parser.py
spinqit_task_manager/compiler/qasm/__init__.py
spinqit_task_manager/compiler/qasm/grammar/__init__.py
spinqit_task_manager/compiler/qasm/include/__init__.py
spinqit_task_manager/compiler/qasm/include/qelib1.inc
spinqit_task_manager/compiler/translator/__init__.py
spinqit_task_manager/compiler/translator/gate_converter.py
spinqit_task_manager/compiler/translator/qiskit_to_spinq.py
spinqit_task_manager/model/Ising_gate.py
spinqit_task_manager/model/__init__.py
spinqit_task_manager/model/basic_gate.py
spinqit_task_manager/model/circuit.py
spinqit_task_manager/model/controlled_gate.py
spinqit_task_manager/model/controlled_gate_decomposer.py
spinqit_task_manager/model/exceptions.py
spinqit_task_manager/model/gates.py
spinqit_task_manager/model/instruction.py
spinqit_task_manager-0.1.7.dist-info/METADATA
spinqit_task_manager-0.1.7.dist-info/WHEEL
spinqit_task_manager-0.1.7.dist-info/entry_points.txt
spinqit_task_manager-0.1.7.dist-info/top_level.txt
spinqit_task_manager-0.1.7.dist-info/RECORD
